scriptabit
