Metadata-Version: 2.1
Name: scriptabit
Version: 2.1.1
Summary: Python scripting for Habitica via the API
Home-page: https://github.com/DC23/scriptabit
Author: JugglinDan
Author-email: jugglindan@gmail.com
License: Apache 2.0
Keywords: Habitica,HabitRPG,Trello
Platform: any
Classifier: Development Status :: 5 - Production/Stable
Classifier: Programming Language :: Python :: 2
Classifier: Programming Language :: Python :: 2.7
Classifier: Programming Language :: Python :: 3
Classifier: Environment :: Console
Classifier: Intended Audience :: End Users/Desktop
Classifier: License :: OSI Approved :: Apache Software License
Classifier: Operating System :: OS Independent
Classifier: Topic :: Games/Entertainment :: Role-Playing
Classifier: Topic :: Utilities
Provides-Extra: dev
Provides-Extra: test
